disambigufile/__init__.py
disambigufile/disambigufile.py
disambigufile-0.3.2.dist-info/LICENSE
disambigufile-0.3.2.dist-info/WHEEL
disambigufile-0.3.2.dist-info/METADATA
disambigufile-0.3.2.dist-info/RECORD
