Metadata-Version: 2.1
Name: disambigufile
Version: 0.3.2
Summary: Class with file-like interface to a file found in provided search path
Home-page: https://github.com/datagazing/disambigufile
Author: Brendan Strejcek
Author-email: brendan@datagazing.com
Requires-Python: >=3.7
Classifier: License :: OSI Approved :: MIT License
Requires-Dist: attrs
